typer_tinydb/__init__.py
typer_tinydb/__main__.py
typer_tinydb/static/config.json
typer_tinydb/tdb.py
typer_tinydb/tests/__init__.py
typer_tinydb/tests/test_upsert.py
typer_tinydb/utils.py
typer_tinydb-0.1.4.post0.dist-info/LICENSE
typer_tinydb-0.1.4.post0.dist-info/METADATA
typer_tinydb-0.1.4.post0.dist-info/WHEEL
typer_tinydb-0.1.4.post0.dist-info/entry_points.txt
typer_tinydb-0.1.4.post0.dist-info/RECORD
