Metadata-Version: 2.1
Name: typer-tinydb
Version: 0.1.4.post0
Summary: A Python Typer CLI subcommand boilerplate to manage config files using tinydb
Home-page: https://arnos-stuff.github.io/typer-tinydb/
Author: arnos-stuff
Author-email: bcda0276@gmail.com
Requires-Python: >=3.8.1,<4.0
Classifier: Programming Language :: Python :: 3
Classifier: Programming Language :: Python :: 3.9
Classifier: Programming Language :: Python :: 3.10
Classifier: Programming Language :: Python :: 3.11
Requires-Dist: tinydb (>=4.7.1,<5.0.0)
Requires-Dist: typer[all] (>=0.7.0,<0.8.0) ; python_version < "3.10"
Requires-Dist: typer[all] (>=0.9.0) ; python_version >= "3.10"
